autopr/__init__.py
autopr/__main__.py
autopr/config.py
autopr/database.py
autopr/github.py
autopr/repo.py
autopr/util.py
autopr/workdir.py
auto_pr-1.2.0.dist-info/METADATA
auto_pr-1.2.0.dist-info/WHEEL
auto_pr-1.2.0.dist-info/entry_points.txt
auto_pr-1.2.0.dist-info/licenses/LICENSE
auto_pr-1.2.0.dist-info/RECORD
