Metadata-Version: 2.4
Name: auto-pr
Version: 1.2.0
Summary: Perform bulk updates across repositories
Project-URL: Homepage, https://github.com/getyourguide/auto-pr
Project-URL: Repository, https://github.com/getyourguide/auto-pr
Author: GetYourGuide GmbH
License: Apache-2.0
License-File: LICENSE
Requires-Python: <4.0,>=3.9.2
Requires-Dist: click==8.1.8
Requires-Dist: cryptography>=45.0.0
Requires-Dist: marshmallow-dataclass==8.7.1
Requires-Dist: marshmallow==4.0.1
Requires-Dist: pygithub==2.8.1
Requires-Dist: pyyaml==6.0.3
Requires-Dist: single-source==0.4.0
Provides-Extra: dev
Requires-Dist: coverage>=7.0.0; extra == 'dev'
Requires-Dist: pre-commit>=4.0.0; extra == 'dev'
Requires-Dist: pytest-cov>=6.0.0; extra == 'dev'
Requires-Dist: pytest-socket>=0.7.0; extra == 'dev'
Requires-Dist: pytest>=8.0.0; extra == 'dev'
Requires-Dist: setuptools==80.9.0; extra == 'dev'
Requires-Dist: wheel>=0.44.0; extra == 'dev'
